loop_controller/__init__.py
loop_controller/mean_controller.py
loop_controller/pid_controller.py
loop_controller-0.1.2.dev0.dist-info/METADATA
loop_controller-0.1.2.dev0.dist-info/WHEEL
loop_controller-0.1.2.dev0.dist-info/top_level.txt
loop_controller-0.1.2.dev0.dist-info/RECORD
