Metadata-Version: 2.1
Name: loop-controller
Version: 0.1.2.dev0
Summary: Loop controllers for managing execution intervals
Home-page: https://github.com/topermaper/loop-controller.git
Author: Marcos Edo Atienza
Author-email: topermaper@gmail.com
License: UNKNOWN
Platform: UNKNOWN
Classifier: Programming Language :: Python :: 3
Classifier: License :: OSI Approved :: MIT License
Classifier: Operating System :: OS Independent
Requires-Python: >=3.6
